pyAMI/LICENSE.txt
pyAMI/__init__.py
pyAMI/app.py
pyAMI/client.py
pyAMI/config.py
pyAMI/exception.py
pyAMI/httpclient.py
pyAMI/modes.py
pyAMI/object.py
pyAMI/transform.py
pyAMI/utils.py
pyAMI_core-5.1.2.data/scripts/ami
pyAMI_core-5.1.2.data/scripts/ami.bat
pyAMI_core-5.1.2.dist-info/METADATA
pyAMI_core-5.1.2.dist-info/WHEEL
pyAMI_core-5.1.2.dist-info/top_level.txt
pyAMI_core-5.1.2.dist-info/RECORD
