Metadata-Version: 2.1
Name: pyAMI-core
Version: 5.1.2
Summary: Python ATLAS Metadata Interface (pyAMI)
Home-page: http://ami.in2p3.fr/
Author: Jerome ODIER, Jerome FULACHIER, Fabian LAMBERT, Solveig ALBRAND
Author-email: jerome.odier@lpsc.in2p3.fr, jerome.fulachier@lpsc.in2p3.fr, fabian.lambert@lpsc.in2p3.fr, solveig.albrand@lpsc.in2p3.fr
License: CeCILL-C
Platform: any
Requires-Dist: argparse
Requires-Dist: argparseplus
Requires-Dist: tiny-xslt
